flask_restless/__init__.py
flask_restless/exceptions.py
flask_restless/helpers.py
flask_restless/manager.py
flask_restless/registry.py
flask_restless/search.py
flask_restless/serialization.py
flask_restless/typehints.py
flask_restless/views/__init__.py
flask_restless/views/base.py
flask_restless/views/helpers.py
flask_restless/views/relationships.py
flask_restless/views/resources.py
flask_restless_ng-3.3.0.dist-info/licenses/LICENSE.AGPL
flask_restless_ng-3.3.0.dist-info/licenses/LICENSE.BSD
flask_restless_ng-3.3.0.dist-info/licenses/LICENSE.md
flask_restless_ng-3.3.0.dist-info/METADATA
flask_restless_ng-3.3.0.dist-info/WHEEL
flask_restless_ng-3.3.0.dist-info/top_level.txt
flask_restless_ng-3.3.0.dist-info/RECORD
