Metadata-Version: 2.4
Name: Flask-Restless-NG
Version: 3.3.0
Summary: A fork of Flask-Restless with updated dependencies and bug fixes
Author-email: Jeffrey Finkelstein <jeffrey.finkelstein@gmail.com>, Maksym Revutskyi <maksym.revutskyi@gmail.com>
Maintainer-email: Maksym Revutskyi <maksym.revutskyi@gmail.com>
License: GNU AGPLv3+ or BSD
Project-URL: Homepage, https://github.com/mrevutskyi/flask-restless-ng
Project-URL: Documentation, https://flask-restless-ng.readthedocs.org
Project-URL: Repository, https://github.com/mrevutskyi/flask-restless-ng
Project-URL: Download, https://pypi.python.org/pypi/Flask-Restless-NG
Project-URL: Bug Tracker, https://github.com/mrevutskyi/flask-restless-ng/issues
Keywords: ReST,API,Flask,SQLAlchemy,JSON API
Classifier: Development Status :: 5 - Production/Stable
Classifier: Environment :: Web Environment
Classifier: Framework :: Flask
Classifier: Intended Audience :: Developers
Classifier: Operating System :: OS Independent
Classifier: Programming Language :: Python
Classifier: Programming Language :: Python :: 3
Classifier: Programming Language :: Python :: 3.8
Classifier: Programming Language :: Python :: 3.9
Classifier: Programming Language :: Python :: 3.10
Classifier: Programming Language :: Python :: 3.11
Classifier: Programming Language :: Python :: 3.12
Classifier: Topic :: Database :: Front-Ends
Classifier: Topic :: Internet :: WWW/HTTP
Classifier: Topic :: Software Development :: Libraries :: Python Modules
Requires-Python: >=3.8
License-File: LICENSE.AGPL
License-File: LICENSE.BSD
License-File: LICENSE.md
Requires-Dist: flask<3.1,>=2.2
Requires-Dist: sqlalchemy<2.1,>=1.4.18
Requires-Dist: python-dateutil>2.2
Requires-Dist: MarkupSafe>=2.0
Provides-Extra: dev
Requires-Dist: pytest>=7.0; extra == "dev"
Requires-Dist: pytest-cov>=3.0; extra == "dev"
Requires-Dist: flake8>=5.0; extra == "dev"
Requires-Dist: isort>=5.0; extra == "dev"
Requires-Dist: mypy>=0.990; extra == "dev"
Requires-Dist: tox>=4.0; extra == "dev"
Requires-Dist: build>=1.0; extra == "dev"
Provides-Extra: doc
Requires-Dist: Sphinx>=5.0; extra == "doc"
Provides-Extra: test
Requires-Dist: pytest>=7.0; extra == "test"
Requires-Dist: pytest-cov>=3.0; extra == "test"
Requires-Dist: jsonschema>=4.0; extra == "test"
Requires-Dist: flask-sqlalchemy>=3.0; extra == "test"
Dynamic: license-file
